Elivelton/__init__.py
Elivelton/multiplicacao_strassen.py
Elivelton/subarray_maximo.py
EliveltonAlgoritmosII-0.1.dist-info/METADATA
EliveltonAlgoritmosII-0.1.dist-info/WHEEL
EliveltonAlgoritmosII-0.1.dist-info/top_level.txt
EliveltonAlgoritmosII-0.1.dist-info/RECORD
