Metadata-Version: 2.1
Name: EliveltonAlgoritmosII
Version: 0.1
Summary: Algoritmos de subarray máximo e multiplicação de Strassen
Home-page: https://github.com/xxvelho/EliveltonAlgoritmosII
Author: Elivelton Bouteille
Author-email: eliveltoncontact@gmail.com
Classifier: Programming Language :: Python :: 3
Classifier: License :: OSI Approved :: MIT License
Classifier: Operating System :: OS Independent
Requires-Python: >=3.6
Requires-Dist: numpy
